LI_AWS_Deploy-3.4.18.dist-info/DESCRIPTION.rst
LI_AWS_Deploy-3.4.18.dist-info/METADATA
LI_AWS_Deploy-3.4.18.dist-info/RECORD
LI_AWS_Deploy-3.4.18.dist-info/WHEEL
LI_AWS_Deploy-3.4.18.dist-info/entry_points.txt
LI_AWS_Deploy-3.4.18.dist-info/metadata.json
LI_AWS_Deploy-3.4.18.dist-info/top_level.txt
test_files/__init__.py
tools/__init__.py
tools/__main__.py
tools/compress.py
tools/config.py
tools/deploy.py
tools/docker.py
tools/help.py
tools/li_tabulate.py
tools/lists.py
tools/messages.py
tools/run.py
tools/settings.py
tools/tests.py
tools/tunnel.py
tools/utils.py
tools/version.py
