Metadata-Version: 2.0
Name: LI-AWS-Deploy
Version: 3.4.18
Summary: Dev tools for Loja Integrada Web Applications
Home-page: UNKNOWN
Author: Chris Maillefaud
Author-email: UNKNOWN
License: UNKNOWN
Keywords: aws deploy
Platform: UNKNOWN
Classifier: Development Status :: 4 - Beta
Classifier: Intended Audience :: Developers
Classifier: Topic :: Software Development :: Build Tools
Classifier: Programming Language :: Python :: 3.5
Requires-Dist: GitPython
Requires-Dist: PyGithub
Requires-Dist: Unidecode
Requires-Dist: awscli
Requires-Dist: awsebcli
Requires-Dist: coverage
Requires-Dist: datadog
Requires-Dist: decorator
Requires-Dist: docopt
Requires-Dist: gitdb
Requires-Dist: ipdb
Requires-Dist: nose
Requires-Dist: requests (<=2.9.1)
Requires-Dist: slackweb
